biocircuitry/__init__.py
biocircuitry/abstractClasses.py
biocircuitry/clustering.py
biocircuitry/matrix.py
biocircuitry/sgd.py
biocircuitry/testClustering.py
biocircuitry/testMatrix.py
biocircuitry/testSGD.py
biocircuitry/testVector.py
biocircuitry/vector.py
biocircuitry-0.0.1.dist-info/LICENSE
biocircuitry-0.0.1.dist-info/METADATA
biocircuitry-0.0.1.dist-info/WHEEL
biocircuitry-0.0.1.dist-info/top_level.txt
biocircuitry-0.0.1.dist-info/RECORD
